pip_downloader/__init__.py
pip_downloader-0.2.dist-info/LICENSE
pip_downloader-0.2.dist-info/METADATA
pip_downloader-0.2.dist-info/WHEEL
pip_downloader-0.2.dist-info/entry_points.txt
pip_downloader-0.2.dist-info/top_level.txt
pip_downloader-0.2.dist-info/RECORD
