Metadata-Version: 1.0
Name: pip-downloader
Version: 0.2
Summary: Download packages from pip for offline usage.
Home-page: https://github.com/AbdealiJK/pip-downloader
Author: AbdealiJK
Author-email: abdealikothari@gmail.com
License: MIT
Platform: UNKNOWN
